cloudia/__init__.py
cloudia/main.py
cloudia/pandas_accessor.py
cloudia/utils.py
cloudia/word_data.py
cloudia-0.2.2.dist-info/entry_points.txt
cloudia-0.2.2.dist-info/LICENSE
cloudia-0.2.2.dist-info/WHEEL
cloudia-0.2.2.dist-info/METADATA
cloudia-0.2.2.dist-info/RECORD
