Metadata-Version: 2.1
Name: cloudia
Version: 0.2.2
Summary: Tools to easily create a word cloud
Home-page: https://github.com/vaaaaanquish/cloudia
License: MIT
Keywords: wordcloud,matplotlib
Author: vaaaaanquish
Author-email: 6syun9@gmail.com
Requires-Python: >=3.6,<4.0
Classifier: License :: OSI Approved :: MIT License
Classifier: Programming Language :: Python :: 3
Classifier: Programming Language :: Python :: 3.6
Classifier: Programming Language :: Python :: 3.7
Classifier: Programming Language :: Python :: 3.8
Requires-Dist: japanize_matplotlib (>=1.1.1,<2.0.0)
Requires-Dist: joblib
Requires-Dist: matplotlib
Requires-Dist: nagisa
Requires-Dist: pandas
Requires-Dist: wordcloud
Requires-Dist: wurlitzer
Project-URL: Repository, https://github.com/vaaaaanquish/cloudia
